ze2nb_cli/__init__.py
ze2nb_cli/cli.py
ze2nb_cli-1.0.2.dist-info/LICENSE
ze2nb_cli-1.0.2.dist-info/METADATA
ze2nb_cli-1.0.2.dist-info/WHEEL
ze2nb_cli-1.0.2.dist-info/entry_points.txt
ze2nb_cli-1.0.2.dist-info/top_level.txt
ze2nb_cli-1.0.2.dist-info/RECORD
