Metadata-Version: 2.1
Name: ze2nb-cli
Version: 1.0.2
Summary: A simple CLI for ze2nb
Home-page: https://github.com/joeyism/ze2nb-cli
Author: joeyism
Author-email: joeyism@gmail.com
License: UNKNOWN
Download-URL: https://github.com/joeyism/ze2nb-cli/archive/1.0.2.tar.gz
Keywords: ze2nb,cli,zeppelin,jupyter,notebook,ipynb,note.json
Platform: UNKNOWN
Requires-Dist: ze2nb
